Design_files/Exp_1/lab_exp/demux_design/demux_1to4.v
module demux_1to4(
    input wire din,
    input wire [1:0] sel,
    output reg [3:0] dout
);
    always @(*) begin
        dout = 4'b0000;  // Default output
        case (sel)
            2'b00: dout[0] = din;
            2'b01: dout[1] = din;
            2'b10: dout[2] = din;
            2'b11: dout[3] = din;
        endcase
    end
endmodule

Design_files/Exp_1/lab_exp/demux_design/tb_demux.v
module tb_demux;
    reg din;
    reg [1:0] sel;
    wire [3:0] dout;
    
    demux_1to4 uut (
        .din(din),
        .sel(sel),
        .dout(dout)
    );

    initial begin
        $monitor("Time = %0t | din = %b | sel = %b | dout = %b", $time, din, sel, dout);
        $dumpfile("tb_demux");
        $dumpvars(0,tb_demux);

        din = 1; sel = 2'b00; #10;
        din = 1; sel = 2'b01; #10;
        din = 1; sel = 2'b10; #10;
        din = 1; sel = 2'b11; #10;
        din = 0; sel = 2'b00; #10;
        din = 0; sel = 2'b01; #10;
        din = 0; sel = 2'b10; #10;
        din = 0; sel = 2'b11; #10;

        $finish;
    end
endmodule

Design_files/Exp_1/lab_exp/demux_design/tb_demux.vcd
$date
	Tue Mar  4 08:18:35 2025
$end
$version
	Icarus Verilog
$end
$timescale
	1s
$end
$scope module tb_demux $end
$var wire 4 ! dout [3:0] $end
$var reg 1 " din $end
$var reg 2 # sel [1:0] $end
$scope module uut $end
$var wire 1 " din $end
$var wire 2 $ sel [1:0] $end
$var reg 4 % dout [3:0] $end
$upscope $end
$upscope $end
$enddefinitions $end
$comment Show the parameter values. $end
$dumpall
$end
#0
$dumpvars
b1 %
b0 $
b0 #
1"
b1 !
$end
#10
b10 !
b10 %
b1 #
b1 $
#20
b100 !
b100 %
b10 #
b10 $
#30
b1000 !
b1000 %
b11 #
b11 $
#40
b0 !
b0 %
b0 #
b0 $
0"
#50
b1 #
b1 $
#60
b10 #
b10 $
#70
b11 #
b11 $
