Design_files/Exp_3/lab_exp/alu/alu_8bit.v
module alu_8bit (
    input [7:0] A,      // 8-bit input A
    input [7:0] B,      // 8-bit input B
    input [3:0] opcode, // 4-bit opcode to select the operation (16 operations)
    output reg [7:0] result, // 8-bit result
    output reg carry_out,     // Carry out for addition and shift
    output reg zero          // Zero flag
);

    always @(*) begin
        // Reset the result and flags
        result = 8'b0;
        carry_out = 0;
        zero = 0;

        // ALU operation based on opcode
        case (opcode)
            4'b0000: {carry_out, result} = A + B;     // Addition with carry
            4'b0001: result = A - B;                 // Subtraction
            4'b0010: result = A & B;                 // AND operation
            4'b0011: result = A | B;                 // OR operation
            4'b0100: result = A ^ B;                 // XOR operation
            4'b0101: result = ~(A & B);              // NAND operation
            4'b0110: result = ~(A | B);              // NOR operation
            4'b0111: result = ~(A ^ B);              // XNOR operation
            4'b1000: {carry_out, result} = {A, 1'b0}; // Logical left shift (A << 1)
            4'b1001: result = A >> 1;                // Logical right shift (A >> 1)
            4'b1010: result = (A << 1) | (A >> 7);   // Rotate left (ROL)
            4'b1011: result = (A >> 1) | (A << 7);   // Rotate right (ROR)
            4'b1100: result = A <<< 1;               // Arithmetic left shift
            4'b1101: result = A >>> 1;               // Arithmetic right shift
            4'b1110: result = A * B;                 // Multiplication (truncated to 8 bits)
            4'b1111: result = A / (B == 0 ? 1 : B);  // Division (Avoid division by zero)
            default: result = 8'b0;                  // Default case (shouldn't happen)
        endcase
        
        // Set zero flag if result is zero
        if (result == 8'b0)
            zero = 1;
    end
endmodule

Design_files/Exp_3/lab_exp/alu/tb_alu_8bit.v
module tb_alu_8bit;
    reg [7:0] A, B;
    reg [3:0] opcode;
    wire [7:0] result;
    wire carry_out, zero;

    alu_8bit uut (
        .A(A),
        .B(B),
        .opcode(opcode),
        .result(result),
        .carry_out(carry_out),
        .zero(zero)
    );

    initial begin
        $monitor("Time=%0t | A=%b | B=%b | Opcode=%b | Result=%b | Carry=%b | Zero=%b", 
                 $time, A, B, opcode, result, carry_out, zero);
        $dumpfile("tb_alu_8bit.vcd");
    $dumpvars(0,tb_alu_8bit);

        A = 8'b00001111; B = 8'b00000001; opcode = 4'b0000; #10; // Addition
        A = 8'b00001111; B = 8'b00000001; opcode = 4'b0001; #10; // Subtraction
        A = 8'b10101010; B = 8'b11001100; opcode = 4'b0010; #10; // AND
        A = 8'b10101010; B = 8'b11001100; opcode = 4'b0011; #10; // OR
        A = 8'b10101010; B = 8'b11001100; opcode = 4'b0100; #10; // XOR
        A = 8'b00001111; opcode = 4'b1000; #10; // Left shift
        A = 8'b10001111; opcode = 4'b1001; #10; // Right shift
        A = 8'b10001111; opcode = 4'b1010; #10; // Rotate left
        A = 8'b10001111; opcode = 4'b1011; #10; // Rotate right
        A = 8'b00000011; B = 8'b00000010; opcode = 4'b1110; #10; // Multiplication
        A = 8'b00001000; B = 8'b00000010; opcode = 4'b1111; #10; // Division

        $finish;
    end
endmodule

Design_files/Exp_3/lab_exp/alu/tb_alu_8bit.vcd
$date
	Tue Mar  4 08:13:43 2025
$end
$version
	Icarus Verilog
$end
$timescale
	1s
$end
$scope module tb_alu_8bit $end
$var wire 1 ! zero $end
$var wire 8 " result [7:0] $end
$var wire 1 # carry_out $end
$var reg 8 $ A [7:0] $end
$var reg 8 % B [7:0] $end
$var reg 4 & opcode [3:0] $end
$scope module uut $end
$var wire 8 ' A [7:0] $end
$var wire 8 ( B [7:0] $end
$var wire 4 ) opcode [3:0] $end
$var reg 1 # carry_out $end
$var reg 8 * result [7:0] $end
$var reg 1 ! zero $end
$upscope $end
$upscope $end
$enddefinitions $end
$comment Show the parameter values. $end
$dumpall
$end
#0
$dumpvars
b10000 *
b0 )
b1 (
b1111 '
b0 &
b1 %
b1111 $
0#
b10000 "
0!
$end
#10
b1110 "
b1110 *
b1 &
b1 )
#20
b10001000 "
b10001000 *
b10 &
b10 )
b11001100 %
b11001100 (
b10101010 $
b10101010 '
#30
b11101110 "
b11101110 *
b11 &
b11 )
#40
b1100110 "
b1100110 *
b100 &
b100 )
#50
b11110 "
b11110 *
b1000 &
b1000 )
b1111 $
b1111 '
#60
b1000111 "
b1000111 *
b1001 &
b1001 )
b10001111 $
b10001111 '
#70
b11111 "
b11111 *
b1010 &
b1010 )
#80
b11000111 "
b11000111 *
b1011 &
b1011 )
#90
b110 "
b110 *
b1110 &
b1110 )
b10 %
b10 (
b11 $
b11 '
#100
b100 "
b100 *
b1111 &
b1111 )
b1000 $
b1000 '
